{
  "type": "Feature",
  "properties": {
    "iso:country":"MX",
    "sg:address":"Ave. Amores 707",
    "sg:city":"Col. Del Valle, D.F.",
    "sg:classifiers":[
        {
            "category":"Professional",
            "subcategory":"Computer Services",
            "type":"Services"
        }
    ],
    "sg:postcode":"03100",
    "sg:tags":[
        "library",
        "libraries",
        "archives",
        "museums",
        "bibliographic-information",
        "bibliographic-records",
        "cataloging",
        "ill",
        "inter-library-loan",
        "metadata",
        "book-data"
    ],
    "sg:website":"http://www.oclc.org/",
    "wof:name":"OCLC",
    "wof:placetype":"venue"
},
  "geometry": {"coordinates":[-99.1655564,19.3871733],"type":"Point"}
}