{
  "type": "Feature",
  "properties": {
    "counts:concordances_total":"1",
    "counts:languages_official":"0",
    "counts:languages_spoken":"0",
    "counts:languages_total":"0",
    "counts:names_colloquial":"0",
    "counts:names_languages":"0",
    "counts:names_prefered":"0",
    "counts:names_total":"0",
    "counts:names_variant":"0",
    "etdf:deprecated":"2016-07-21",
    "iso:country":"MX",
    "sg:address":"-keine-",
    "sg:city":"-keine-",
    "sg:phone":"+49 2222/358",
    "sg:postcode":"11111",
    "wof:name":"Jovanas Musik Seite",
    "wof:placetype":"venue"
},
  "geometry": {"coordinates":[-99.149773,19.40904],"type":"Point"}
}