{
  "type": "Feature",
  "properties": {
    "iso:country":"MX",
    "sg:address":"Rio de la plata 300",
    "sg:city":"San Pedro Garza Garcia",
    "sg:classifiers":[
        {
            "category":"Professional",
            "subcategory":"Computer Services",
            "type":"Services"
        }
    ],
    "sg:postcode":"66220",
    "sg:tags":[
        "mobile",
        "sms",
        "mms",
        "wap",
        "payment",
        "billing",
        "mobile-advertising",
        "mobile-marketing",
        "mobile-internet",
        "mobile-banking",
        "mobile-messaging",
        "wireless",
        "gprs",
        "umts",
        "gateway",
        "roaming",
        "games",
        "ringtones",
        "mp3",
        "music"
    ],
    "sg:website":"http://www.binbit.com",
    "wof:name":"Binbit",
    "wof:placetype":"venue"
},
  "geometry": {"coordinates":[-100.3760321,25.6600605],"type":"Point"}
}