{
  "type": "Feature",
  "properties": {
    "counts:concordances_total":"1",
    "counts:languages_official":"0",
    "counts:languages_spoken":"0",
    "counts:languages_total":"0",
    "counts:names_colloquial":"0",
    "counts:names_languages":"0",
    "counts:names_prefered":"0",
    "counts:names_total":"0",
    "counts:names_variant":"0",
    "etdf:deprecated":"2016-07-21",
    "iso:country":"MX",
    "sg:address":"468 Pollen St ",
    "sg:city":"Thames",
    "sg:orig_category":"Industrial: Equipment And Machinery: Specialist Equipment: Machinery: Sewing Machines",
    "sg:phone":"+64 7-868 8190",
    "sg:province":"Waikato",
    "wof:name":"Christies Sewing Centre & Linen Closet",
    "wof:placetype":"venue"
},
  "geometry": {"coordinates":[-104.41848,20.632469],"type":"Point"}
}