{
  "type": "Feature",
  "properties": {
    "counts:concordances_total":"1",
    "counts:languages_official":"0",
    "counts:languages_spoken":"0",
    "counts:languages_total":"0",
    "counts:names_colloquial":"0",
    "counts:names_languages":"0",
    "counts:names_prefered":"0",
    "counts:names_total":"0",
    "counts:names_variant":"0",
    "etdf:deprecated":"2016-07-21",
    "iso:country":"MX",
    "sg:address":"Counterweg",
    "sg:city":"CS1.1ingen",
    "sg:phone":"+49 30",
    "sg:postcode":"66666",
    "wof:name":"Offizielle Down-runner-clan Homepage",
    "wof:placetype":"venue"
},
  "geometry": {"coordinates":[-100.02153800000001,25.761641],"type":"Point"}
}