{
  "type": "Feature",
  "properties": {
    "counts:concordances_total":"1",
    "counts:languages_official":"0",
    "counts:languages_spoken":"0",
    "counts:languages_total":"0",
    "counts:names_colloquial":"0",
    "counts:names_languages":"0",
    "counts:names_prefered":"0",
    "counts:names_total":"0",
    "counts:names_variant":"0",
    "etdf:deprecated":"2016-07-21",
    "iso:country":"MX",
    "sg:address":"hjzjg 4",
    "sg:city":"hggkuhj",
    "sg:phone":"+49 355/3356",
    "sg:postcode":"43256",
    "wof:name":"Regpkbk",
    "wof:placetype":"venue"
},
  "geometry": {"coordinates":[-98.57122,20.765011],"type":"Point"}
}