{
  "type": "Feature",
  "properties": {
    "counts:concordances_total":"1",
    "counts:languages_official":"0",
    "counts:languages_spoken":"0",
    "counts:languages_total":"0",
    "counts:names_colloquial":"0",
    "counts:names_languages":"0",
    "counts:names_prefered":"0",
    "counts:names_total":"0",
    "counts:names_variant":"0",
    "etdf:deprecated":"2016-07-21",
    "iso:country":"MX",
    "sg:address":"PO Box 51184 ",
    "sg:categories":[
        "sg/services/insurance",
        "services/insurance/health_insurance"
    ],
    "sg:city":"Tawa",
    "sg:classifiers":[
        {
            "category":"Insurance",
            "subcategory":"Health Insurance",
            "type":"Services"
        }
    ],
    "sg:phone":"+64 4-920 5667",
    "sg:province":"Wellington",
    "sg:tags":[
        "pregnancy",
        "specialists",
        "beauty"
    ],
    "wof:name":"The House of Grace Trust Inc. - A Home for Pregnant Teens",
    "wof:placetype":"venue"
},
  "geometry": {"coordinates":[-100.303078,19.11949],"type":"Point"}
}