{
  "type": "Feature",
  "properties": {
    "iso:country":"MX",
    "sg:address":"Calle Brasil No. 8471 Col. Juarez",
    "sg:city":"Tijuana, B.C.",
    "sg:classifiers":[
        {
            "category":"Professional",
            "subcategory":"Computer Services",
            "type":"Services"
        }
    ],
    "sg:postcode":"22040 ",
    "sg:tags":[
        "video-games",
        "blogs",
        "social-interaction",
        "reviews",
        "previews",
        "news",
        "event-coverage",
        "and-video",
        "spanish-speakers",
        "hispanics",
        "latinos",
        "mexico",
        "latin-america"
    ],
    "sg:website":"http://www.buscacorp.com",
    "wof:name":"Busca Corp",
    "wof:placetype":"venue"
},
  "geometry": {"coordinates":[-117.02749470000001,32.5217442],"type":"Point"}
}