{
  "type": "Feature",
  "properties": {
    "counts:concordances_total":"1",
    "counts:languages_official":"0",
    "counts:languages_spoken":"0",
    "counts:languages_total":"0",
    "counts:names_colloquial":"0",
    "counts:names_languages":"0",
    "counts:names_prefered":"0",
    "counts:names_total":"0",
    "counts:names_variant":"0",
    "etdf:deprecated":"2016-07-21",
    "iso:country":"MX",
    "sg:address":"Wienkeskoel 38",
    "sg:city":"Melick",
    "sg:orig_category":"Luchtbehandelings- Apparaten",
    "sg:phone":"+31 475 537 204",
    "sg:postcode":"6074 HG",
    "sg:province":"Limburg",
    "wof:name":"Hendrickx",
    "wof:placetype":"venue"
},
  "geometry": {"coordinates":[-98.924362,20.49721],"type":"Point"}
}