{
  "type": "Feature",
  "properties": {
    "counts:concordances_total":"1",
    "counts:languages_official":"0",
    "counts:languages_spoken":"0",
    "counts:languages_total":"0",
    "counts:names_colloquial":"0",
    "counts:names_languages":"0",
    "counts:names_prefered":"0",
    "counts:names_total":"0",
    "counts:names_variant":"0",
    "etdf:deprecated":"2016-07-21",
    "iso:country":"MX",
    "sg:address":"Kirchstr. 1",
    "sg:city":"Frankenhardt",
    "sg:phone":"+49 4979/592004",
    "sg:postcode":"74587",
    "sg:province":"Baden-W\u00fcrttemberg",
    "wof:name":"Raiffeisenbank Frankenhardt Eg",
    "wof:placetype":"venue"
},
  "geometry": {"coordinates":[-98.65907300000001,18.48597],"type":"Point"}
}