{
  "type": "Feature",
  "properties": {
    "counts:concordances_total":"1",
    "counts:languages_official":"0",
    "counts:languages_spoken":"0",
    "counts:languages_total":"0",
    "counts:names_colloquial":"0",
    "counts:names_languages":"0",
    "counts:names_prefered":"0",
    "counts:names_total":"0",
    "counts:names_variant":"0",
    "etdf:deprecated":"2016-07-21",
    "iso:country":"MX",
    "sg:address":"Postbus 31376",
    "sg:city":"Nymegen",
    "sg:orig_category":"Adviesbureaus Bedrijfsorganisatie",
    "sg:phone":"+31 24 360 6760",
    "sg:postcode":"6503 CJ",
    "sg:province":"Zuid-Holland",
    "sg:website":"http://www.instituut-iem.nl",
    "wof:name":"Iem Bv",
    "wof:placetype":"venue"
},
  "geometry": {"coordinates":[-106.0737,28.630581],"type":"Point"}
}