{
  "type": "Feature",
  "properties": {
    "iso:country":"MX",
    "sg:address":"Autopista Mexico-Puebla 1117",
    "sg:city":"Puebla",
    "sg:classifiers":[
        {
            "category":"Professional",
            "subcategory":"Computer Services",
            "type":"Services"
        }
    ],
    "sg:postcode":"72014",
    "sg:tags":[
        "painting",
        "warehousing",
        "services",
        "logistics",
        "inspection"
    ],
    "sg:website":"http://www.mpi-usa.com",
    "wof:name":"Materials Processing Inc. / Mexico Painting Inc.",
    "wof:placetype":"venue"
},
  "geometry": {"coordinates":[-98.23479620000001,19.1000075],"type":"Point"}
}