{
  "type": "Feature",
  "properties": {
    "counts:concordances_total":"1",
    "counts:languages_official":"0",
    "counts:languages_spoken":"0",
    "counts:languages_total":"0",
    "counts:names_colloquial":"0",
    "counts:names_languages":"0",
    "counts:names_prefered":"0",
    "counts:names_total":"0",
    "counts:names_variant":"0",
    "etdf:deprecated":"2016-07-21",
    "iso:country":"MX",
    "sg:address":"Hg Buurlosewg 4",
    "sg:city":"Harskamp",
    "sg:orig_category":"Honden- En Kattentrimsalons",
    "sg:phone":"+31 318 456 840",
    "sg:postcode":"6732 ES",
    "sg:province":"Gelderland",
    "wof:name":"Francis Schotkamp",
    "wof:placetype":"venue"
},
  "geometry": {"coordinates":[-98.924362,20.49721],"type":"Point"}
}