{
  "type": "Feature",
  "properties": {
    "counts:concordances_total":"1",
    "counts:languages_official":"0",
    "counts:languages_spoken":"0",
    "counts:languages_total":"0",
    "counts:names_colloquial":"0",
    "counts:names_languages":"0",
    "counts:names_prefered":"0",
    "counts:names_total":"0",
    "counts:names_variant":"0",
    "etdf:deprecated":"2016-07-21",
    "iso:country":"MX",
    "sg:address":"J Israelsstr 20",
    "sg:city":"Nymegen",
    "sg:orig_category":"Bodemonderzoek",
    "sg:phone":"+31 24 322 0243",
    "sg:postcode":"6521 MX",
    "sg:province":"Gelderland",
    "wof:name":"Boot Milieuconsult Nijmegen",
    "wof:placetype":"venue"
},
  "geometry": {"coordinates":[-101.956253,23.62574],"type":"Point"}
}